voxtool
