Metadata-Version: 2.1
Name: voxtool
Version: 0.0.2
Summary: VoxTool: A tool for labeling intracranial electrodes on CT images
Home-page: https://github.com/penn-cnt/ieeg-recon/
